djangocms_html_tags/__init__.py
djangocms_html_tags/cms_plugins.py
djangocms_html_tags/forms.py
djangocms_html_tags/models.py
djangocms_html_tags/utils.py
djangocms_html_tags/migrations/0001_initial.py
djangocms_html_tags/migrations/__init__.py
djangocms_html_tags/templates/djangocms_html_tags/form.html
djangocms_html_tags/templates/djangocms_html_tags/html_text.html
djangocms_html_tags/templates/djangocms_html_tags/input.html
tests/__init__.py
tests/settings.py
djangocms_html_tags-1.0.0.dist-info/LICENSE
djangocms_html_tags-1.0.0.dist-info/METADATA
djangocms_html_tags-1.0.0.dist-info/WHEEL
djangocms_html_tags-1.0.0.dist-info/top_level.txt
djangocms_html_tags-1.0.0.dist-info/RECORD
