Metadata-Version: 2.1
Name: djangocms-html-tags
Version: 1.0.0
Summary: # HTML Tags
Requires-Dist: django-cms (>=3.5)
Requires-Dist: djangocms-attributes-field (>=1.0.0)
